ukb_api/__init__.py
ukb_api/module_bulk_data_handler.py
ukb_api/module_genetic_data_handler.py
ukb_api/module_get_fs_summary_stats.py
ukb_api/module_scalar_data_handler.py
ukb_api-0.409.dist-info/LICENSE
ukb_api-0.409.dist-info/METADATA
ukb_api-0.409.dist-info/WHEEL
ukb_api-0.409.dist-info/top_level.txt
ukb_api-0.409.dist-info/RECORD
