Metadata-Version: 2.1
Name: ukb-api
Version: 0.409
Summary: UKB API
Home-page: UNKNOWN
Author: Tigmanshu Chaudhary
License: UNKNOWN
Platform: UNKNOWN
Classifier: Programming Language :: Python :: 3
Classifier: License :: OSI Approved :: MIT License
Classifier: Operating System :: OS Independent
Requires-Python: >=3.6
License-File: LICENSE
Requires-Dist: pandas (==1.1.5)
Requires-Dist: datalad
Requires-Dist: pandas-plink
Requires-Dist: numpy
Requires-Dist: dataclasses
